aliexpress_page_parser/VERSION
aliexpress_page_parser/__init__.py
aliexpress_page_parser/freight_list_parser.py
aliexpress_page_parser/freight_parser.py
aliexpress_page_parser/product_detail_parser.py
aliexpress_page_parser/product_list_parser.py
tests/__init__.py
tests/conftest.py
tests/test_freight_list_parser.py
tests/test_freight_parser.py
tests/test_product_detail_parser.py
tests/test_product_list_parser.py
aliexpress_page_parser-0.0.9.dist-info/METADATA
aliexpress_page_parser-0.0.9.dist-info/WHEEL
aliexpress_page_parser-0.0.9.dist-info/top_level.txt
aliexpress_page_parser-0.0.9.dist-info/RECORD
